setup.py
certifications/__init__.py
certifications.egg-info/PKG-INFO
certifications.egg-info/SOURCES.txt
certifications.egg-info/dependency_links.txt
certifications.egg-info/top_level.txt